COVID19_ES_Py/__init__.py
COVID19_ES_Py/exceptions.py
COVID19_ES_Py/relatorio.py
COVID19_ES_Py/utils.py
COVID19_ES_Py-3.1.0.dist-info/LICENSE
COVID19_ES_Py-3.1.0.dist-info/METADATA
COVID19_ES_Py-3.1.0.dist-info/WHEEL
COVID19_ES_Py-3.1.0.dist-info/top_level.txt
COVID19_ES_Py-3.1.0.dist-info/RECORD
