Metadata-Version: 2.1
Name: COVID19-ES-Py
Version: 3.1.0
Summary: Scraper de boletins de casos de COVID-19 no Espírito Santo.
Home-page: https://github.com/atilioa/COVID19-ES-Py
Author: Atílio Antônio
Author-email: atiliodadalto@protonmail.com
License: GLP-3
Keywords: covid covid19 corona coronavirus brazil espirito-santo es api
Platform: UNKNOWN
Classifier: License :: OSI Approved :: GNU General Public License v3 or later (GPLv3+)
Classifier: Programming Language :: Python :: 3
Classifier: Programming Language :: Python :: 3.6
Classifier: Programming Language :: Python :: 3.7
Classifier: Programming Language :: Python :: 3.8
Requires-Dist: arrow (==0.15.5)
Requires-Dist: attrs (==19.3.0)
Requires-Dist: beautifulsoup4 (==4.9.0)
Requires-Dist: certifi (==2020.4.5.1)
Requires-Dist: chardet (==3.0.4)
Requires-Dist: coverage (==5.1)
Requires-Dist: idna (==2.9)
Requires-Dist: more-itertools (==8.2.0)
Requires-Dist: packaging (==20.3)
Requires-Dist: pluggy (==0.13.1)
Requires-Dist: py (==1.8.1)
Requires-Dist: pyparsing (==3.0.0a1)
Requires-Dist: pytest (==5.4.1)
Requires-Dist: pytest-cov (==2.8.1)
Requires-Dist: python-dateutil (==2.8.1)
Requires-Dist: requests (==2.23.0)
Requires-Dist: six (==1.14.0)
Requires-Dist: soupsieve (==2.0)
Requires-Dist: urllib3 (==1.25.9)
Requires-Dist: wcwidth (==0.1.9)
Requires-Dist: wrapt (==1.12.1)
Requires-Dist: zipp (==3.1.0)
Requires-Dist: rows
Requires-Dist: importlib-metadata (==1.6.0) ; python_version < "3.8"
Requires-Dist: atomicwrites (==1.3.0) ; sys_platform == "win32"
Requires-Dist: colorama (==0.4.3) ; sys_platform == "win32"
